lscl/__init__.py
lscl/errors.py
lscl/lang.py
lscl/parser.py
lscl/renderer.py
lscl/utils.py
lscl-0.5.dist-info/LICENSE.txt
lscl-0.5.dist-info/METADATA
lscl-0.5.dist-info/WHEEL
lscl-0.5.dist-info/RECORD
