Metadata-Version: 2.3
Name: lscl
Version: 0.5
Summary: Logstash configuration language handling
Keywords: logstash,lscl
Author: Thomas Touhey
Author-email: thomas@touhey.fr
Requires-Python: >=3.11,<4.0
Classifier: Development Status :: 4 - Beta
Classifier: Intended Audience :: Developers
Classifier: License :: CeCILL-C Free Software License Agreement (CECILL-C)
Classifier: Natural Language :: English
Classifier: Programming Language :: Python :: 3
Classifier: Programming Language :: Python :: 3 :: Only
Classifier: Typing :: Typed
Requires-Dist: eval-type-backport (>=0.2,<0.3) ; python_version < "3.10"
Requires-Dist: pydantic (>=2.7,<3)
Requires-Dist: typing-extensions (>=4.12,<5)
Project-URL: Bug Tracker, https://gitlab.com/kaquel/lscl/-/issues
Project-URL: Documentation, https://lscl.touhey.pro/
Project-URL: Homepage, https://lscl.touhey.pro/
Project-URL: Source Code, https://gitlab.com/kaquel/lscl
